{
     "users": [
          {
               "id": 1,
               "name": "Gertrudis Tatterton",
               "password": 12345,
               "email": "gtatterton0@ehow.com"
          },
          {
               "id": 2,
               "name": "Gail Newbatt",
               "password": 12345,
               "email": "gnewbatt1@un.org"
          },
          {
               "id": 3,
               "name": "Walliw Wilstead",
               "password": 12345,
               "email": "wwilstead2@tripadvisor.com"
          },
          {
               "id": 4,
               "name": "Abran Proback",
               "password": 12345,
               "email": "aproback3@theglobeandmail.com"
          },
          {
               "id": 5,
               "name": "Roda Chappelow",
               "password": 12345,
               "email": "rchappelow4@oaic.gov.au"
          },
          {
               "id": 6,
               "name": "Karney Wylie",
               "password": 12345,
               "email": "kwylie5@miitbeian.gov.cn"
          },
          {
               "id": 7,
               "name": "Cammi Pimbley",
               "password": 12345,
               "email": "cpimbley6@nyu.edu"
          },
          {
               "id": 8,
               "name": "Gavra Manning",
               "password": 12345,
               "email": "gmanning7@lycos.com"
          },
          {
               "id": 9,
               "name": "Zachary Seward",
               "password": 12345,
               "email": "zseward8@oracle.com"
          },
          {
               "id": 10,
               "name": "Chucho Norssister",
               "password": 12345,
               "email": "cnorssister9@mayoclinic.com"
          }
     ],
     "companies": [
          {
               "id": 1,
               "company_logo": "https://logolook.net/wp-content/uploads/2021/11/HDFC-Bank-Logo.png",
               "company_name": "HDFC Bank",
               "company_type": "Bank",
               "stock_exchange": "NSE",
               "total_shares": 50000,
               "cost_per_share": 4210,
               "price_action": 12
          },
          {
               "id": 2,
               "company_logo": "https://www.jetspot.in/wp-content/uploads/2018/03/reliance-logo.jpg",
               "company_name": "Reliance Industries",
               "company_type": "Oil",
               "stock_exchange": "BSE",
               "total_shares": 20000,
               "cost_per_share": 2132,
               "price_action": 4
          },
          {
               "company_logo": "masai",
               "company_name": "#shanti_venue",
               "company_type": "",
               "stock_exchange": "",
               "total_shares": "900000000",
               "cost_per_share": "1000000",
               "price_action": "6525955",
               "id": 3
          }
     ]
}
